chaostoolkit_utils/__init__.py
chaostoolkit_utils/probes.py
tests/__init__.py
tests/test_chaostoolkit_utils.py
chaostoolkit_utils-0.1.0.dist-info/LICENSE
chaostoolkit_utils-0.1.0.dist-info/METADATA
chaostoolkit_utils-0.1.0.dist-info/WHEEL
chaostoolkit_utils-0.1.0.dist-info/top_level.txt
chaostoolkit_utils-0.1.0.dist-info/RECORD
