Metadata-Version: 2.1
Name: chaostoolkit-utils
Version: 0.1.0
Summary: This package contains utility actions/probes/controls for chaostoolkit
Home-page: https://github.com/sky-uk/chaostoolkit-utils
Author: Marco Masetti
Author-email: marco.masetti@sky.uk
License: Revised BSD License
Keywords: chaostoolkit
Platform: UNKNOWN
Classifier: Development Status :: 2 - Pre-Alpha
Classifier: Intended Audience :: Developers
Classifier: License :: OSI Approved :: BSD License
Classifier: Natural Language :: English
Classifier: Programming Language :: Python :: 3
Classifier: Programming Language :: Python :: 3.7
Classifier: Programming Language :: Python :: 3.8
Classifier: Programming Language :: Python :: 3.9
License-File: LICENSE
